funksignal/__init__.py
funksignal/signal.py
funksignal-0.1.0.dist-info/LICENSE
funksignal-0.1.0.dist-info/METADATA
funksignal-0.1.0.dist-info/WHEEL
funksignal-0.1.0.dist-info/top_level.txt
funksignal-0.1.0.dist-info/RECORD
