Metadata-Version: 2.2
Name: funksignal
Version: 0.1.0
Summary: funksignal is a signaling library for event-driven programming
Home-page: https://github.com/Dreamfarer/funksignal
Author: Dreamfarer
Classifier: Programming Language :: Python :: 3
Classifier: License :: OSI Approved :: GNU Affero General Public License v3
Classifier: Operating System :: OS Independent
Requires-Python: >=3.9
License-File: LICENSE
Dynamic: author
Dynamic: classifier
Dynamic: description
Dynamic: description-content-type
Dynamic: home-page
Dynamic: requires-python
Dynamic: summary
